[{"date":"2023-11-14T23:00:00.889Z","price":11994,"PMH":9820,"TEU":318,"EDCGAS":0,"simulated":false},{"date":"2023-11-15T00:00:00.892Z","price":11601,"PMH":9326,"TEU":318,"EDCGAS":0,"simulated":false},{"date":"2023-11-15T01:00:00.893Z","price":11477,"PMH":9082,"TEU":318,"EDCGAS":0,"simulated":false},{"date":"2023-11-15T02:00:00.895Z","price":11660,"PMH":9148,"TEU":318,"EDCGAS":0,"simulated":false},{"date":"2023-11-15T03:00:00.897Z","price":11675,"PMH":9154,"TEU":318,"EDCGAS":0,"simulated":false},{"date":"2023-11-15T04:00:00.898Z","price":12205,"PMH":9814,"TEU":318,"EDCGAS":0,"simulated":false},{"date":"2023-11-15T05:00:00.900Z","price":13306,"PMH":11217,"TEU":318,"EDCGAS":0,"simulated":false},{"date":"2023-11-15T06:00:00.901Z","price":14971,"PMH":13376,"TEU":318,"EDCGAS":0,"simulated":false},{"date":"2023-11-15T07:00:00.903Z","price":17997,"PMH":13833,"TEU":2857,"EDCGAS":0,"simulated":false},{"date":"2023-11-15T08:00:00.905Z","price":16151,"PMH":12010,"TEU":2857,"EDCGAS":0,"simulated":false},{"date":"2023-11-15T09:00:00.906Z","price":19673,"PMH":10712,"TEU":7298,"EDCGAS":0,"simulated":false},{"date":"2023-11-15T10:00:00.942Z","price":18786,"PMH":9925,"TEU":7298,"EDCGAS":0,"simulated":false},{"date":"2023-11-15T11:00:00.945Z","price":18732,"PMH":9795,"TEU":7298,"EDCGAS":0,"simulated":false},{"date":"2023-11-15T12:00:00.946Z","price":18566,"PMH":9655,"TEU":7298,"EDCGAS":0,"simulated":false},{"date":"2023-11-15T13:00:00.948Z","price":14088,"PMH":9656,"TEU":2857,"EDCGAS":0,"simulated":false},{"date":"2023-11-15T14:00:00.950Z","price":14340,"PMH":9885,"TEU":2857,"EDCGAS":0,"simulated":false},{"date":"2023-11-15T15:00:00.952Z","price":16284,"PMH":12067,"TEU":2857,"EDCGAS":0,"simulated":false},{"date":"2023-11-15T16:00:00.953Z","price":18265,"PMH":14187,"TEU":2857,"EDCGAS":0,"simulated":false},{"date":"2023-11-15T17:00:00.954Z","price":23973,"PMH":15276,"TEU":7298,"EDCGAS":0,"simulated":false},{"date":"2023-11-15T18:00:00.956Z","price":22941,"PMH":14290,"TEU":7298,"EDCGAS":0,"simulated":false},{"date":"2023-11-15T19:00:00.957Z","price":22594,"PMH":13924,"TEU":7298,"EDCGAS":0,"simulated":false},{"date":"2023-11-15T20:00:00.959Z","price":20956,"PMH":12291,"TEU":7298,"EDCGAS":0,"simulated":false},{"date":"2023-11-15T21:00:00.960Z","price":15031,"PMH":10892,"TEU":2857,"EDCGAS":0,"simulated":false},{"date":"2023-11-15T22:00:00.961Z","price":14622,"PMH":10063,"TEU":2857,"EDCGAS":0,"simulated":false}]