[{"date":"2024-10-26T22:00:00.439Z","price":13891,"PMH":10466,"TEU":275,"EDCGAS":0,"simulated":false},{"date":"2024-10-26T23:00:00.440Z","price":13507,"PMH":9981,"TEU":275,"EDCGAS":0,"simulated":false},{"date":"2024-10-27T00:00:00.444Z","price":13526,"PMH":9917,"TEU":275,"EDCGAS":0,"simulated":false},{"date":"2024-10-27T01:00:00.445Z","price":13421,"PMH":9690,"TEU":275,"EDCGAS":0,"simulated":false},{"date":"2024-10-27T02:00:00.445Z","price":13563,"PMH":9797,"TEU":275,"EDCGAS":0,"simulated":false},{"date":"2024-10-27T03:00:00.446Z","price":13462,"PMH":9689,"TEU":275,"EDCGAS":0,"simulated":false},{"date":"2024-10-27T04:00:00.447Z","price":12255,"PMH":8386,"TEU":275,"EDCGAS":0,"simulated":false},{"date":"2024-10-27T05:00:00.448Z","price":13130,"PMH":9502,"TEU":275,"EDCGAS":0,"simulated":false},{"date":"2024-10-27T06:00:00.449Z","price":13466,"PMH":10165,"TEU":275,"EDCGAS":0,"simulated":false},{"date":"2024-10-27T07:00:00.450Z","price":13113,"PMH":9473,"TEU":275,"EDCGAS":0,"simulated":false},{"date":"2024-10-27T08:00:00.451Z","price":10668,"PMH":7414,"TEU":275,"EDCGAS":0,"simulated":false},{"date":"2024-10-27T09:00:00.451Z","price":9467,"PMH":6301,"TEU":275,"EDCGAS":0,"simulated":false},{"date":"2024-10-27T10:00:00.452Z","price":7931,"PMH":4894,"TEU":275,"EDCGAS":0,"simulated":false},{"date":"2024-10-27T11:00:00.453Z","price":7531,"PMH":4585,"TEU":275,"EDCGAS":0,"simulated":false},{"date":"2024-10-27T12:00:00.453Z","price":7540,"PMH":4601,"TEU":275,"EDCGAS":0,"simulated":false},{"date":"2024-10-27T13:00:00.454Z","price":9198,"PMH":6379,"TEU":275,"EDCGAS":0,"simulated":false},{"date":"2024-10-27T14:00:00.455Z","price":8437,"PMH":5271,"TEU":275,"EDCGAS":0,"simulated":false},{"date":"2024-10-27T15:00:00.456Z","price":10718,"PMH":7542,"TEU":275,"EDCGAS":0,"simulated":false},{"date":"2024-10-27T16:00:00.456Z","price":12943,"PMH":9571,"TEU":275,"EDCGAS":0,"simulated":false},{"date":"2024-10-27T17:00:00.457Z","price":13999,"PMH":11287,"TEU":275,"EDCGAS":0,"simulated":false},{"date":"2024-10-27T18:00:00.458Z","price":17513,"PMH":14938,"TEU":275,"EDCGAS":0,"simulated":false},{"date":"2024-10-27T19:00:00.458Z","price":15569,"PMH":13404,"TEU":275,"EDCGAS":0,"simulated":false},{"date":"2024-10-27T20:00:00.459Z","price":14738,"PMH":12524,"TEU":275,"EDCGAS":0,"simulated":false},{"date":"2024-10-27T21:00:00.460Z","price":12986,"PMH":10670,"TEU":275,"EDCGAS":0,"simulated":false},{"date":"2024-10-27T22:00:00.461Z","price":14785,"PMH":12337,"TEU":275,"EDCGAS":0,"simulated":false}]