[{"date":"2024-07-11T22:00:00.952Z","price":12377,"PMH":9894,"TEU":275,"EDCGAS":0,"simulated":false},{"date":"2024-07-11T23:00:00.953Z","price":10954,"PMH":8316,"TEU":275,"EDCGAS":0,"simulated":false},{"date":"2024-07-12T00:00:00.954Z","price":11325,"PMH":8686,"TEU":275,"EDCGAS":0,"simulated":false},{"date":"2024-07-12T01:00:00.954Z","price":10006,"PMH":7350,"TEU":275,"EDCGAS":0,"simulated":false},{"date":"2024-07-12T02:00:00.955Z","price":9387,"PMH":6614,"TEU":275,"EDCGAS":0,"simulated":false},{"date":"2024-07-12T03:00:00.956Z","price":9788,"PMH":7051,"TEU":275,"EDCGAS":0,"simulated":false},{"date":"2024-07-12T04:00:00.956Z","price":10801,"PMH":8148,"TEU":275,"EDCGAS":0,"simulated":false},{"date":"2024-07-12T05:00:00.957Z","price":11490,"PMH":8781,"TEU":275,"EDCGAS":0,"simulated":false},{"date":"2024-07-12T06:00:00.957Z","price":13585,"PMH":8411,"TEU":2796,"EDCGAS":0,"simulated":false},{"date":"2024-07-12T07:00:00.958Z","price":10985,"PMH":5640,"TEU":2796,"EDCGAS":0,"simulated":false},{"date":"2024-07-12T08:00:00.958Z","price":15054,"PMH":4843,"TEU":7697,"EDCGAS":0,"simulated":false},{"date":"2024-07-12T09:00:00.959Z","price":15025,"PMH":4801,"TEU":7697,"EDCGAS":0,"simulated":false},{"date":"2024-07-12T10:00:00.960Z","price":15040,"PMH":4806,"TEU":7697,"EDCGAS":0,"simulated":false},{"date":"2024-07-12T11:00:00.961Z","price":14966,"PMH":4793,"TEU":7697,"EDCGAS":0,"simulated":false},{"date":"2024-07-12T12:00:00.962Z","price":9957,"PMH":4752,"TEU":2796,"EDCGAS":0,"simulated":false},{"date":"2024-07-12T13:00:00.962Z","price":9397,"PMH":4172,"TEU":2796,"EDCGAS":0,"simulated":false},{"date":"2024-07-12T14:00:00.963Z","price":8062,"PMH":2850,"TEU":2796,"EDCGAS":0,"simulated":false},{"date":"2024-07-12T15:00:00.963Z","price":9859,"PMH":4420,"TEU":2796,"EDCGAS":0,"simulated":false},{"date":"2024-07-12T16:00:00.964Z","price":15349,"PMH":4810,"TEU":7697,"EDCGAS":0,"simulated":false},{"date":"2024-07-12T17:00:00.965Z","price":16609,"PMH":6017,"TEU":7697,"EDCGAS":0,"simulated":false},{"date":"2024-07-12T18:00:00.965Z","price":18910,"PMH":8733,"TEU":7697,"EDCGAS":0,"simulated":false},{"date":"2024-07-12T19:00:00.966Z","price":20441,"PMH":10338,"TEU":7697,"EDCGAS":0,"simulated":false},{"date":"2024-07-12T20:00:00.966Z","price":15262,"PMH":10114,"TEU":2796,"EDCGAS":0,"simulated":false},{"date":"2024-07-12T21:00:00.967Z","price":14513,"PMH":9273,"TEU":2796,"EDCGAS":0,"simulated":false}]