[{"date":"2024-02-24T23:00:00.195Z","price":5334,"PMH":533,"TEU":275,"EDCGAS":0,"simulated":false},{"date":"2024-02-25T00:00:00.197Z","price":5195,"PMH":395,"TEU":275,"EDCGAS":0,"simulated":false},{"date":"2024-02-25T01:00:00.199Z","price":5305,"PMH":398,"TEU":275,"EDCGAS":0,"simulated":false},{"date":"2024-02-25T02:00:00.200Z","price":5388,"PMH":400,"TEU":275,"EDCGAS":0,"simulated":false},{"date":"2024-02-25T03:00:00.201Z","price":5426,"PMH":401,"TEU":275,"EDCGAS":0,"simulated":false},{"date":"2024-02-25T04:00:00.203Z","price":5392,"PMH":374,"TEU":275,"EDCGAS":0,"simulated":false},{"date":"2024-02-25T05:00:00.204Z","price":5359,"PMH":399,"TEU":275,"EDCGAS":0,"simulated":false},{"date":"2024-02-25T06:00:00.206Z","price":5257,"PMH":397,"TEU":275,"EDCGAS":0,"simulated":false},{"date":"2024-02-25T07:00:00.208Z","price":5213,"PMH":394,"TEU":275,"EDCGAS":0,"simulated":false},{"date":"2024-02-25T08:00:00.209Z","price":5511,"PMH":378,"TEU":275,"EDCGAS":0,"simulated":false},{"date":"2024-02-25T09:00:00.210Z","price":5135,"PMH":378,"TEU":275,"EDCGAS":0,"simulated":false},{"date":"2024-02-25T10:00:00.212Z","price":5053,"PMH":373,"TEU":275,"EDCGAS":0,"simulated":false},{"date":"2024-02-25T11:00:00.213Z","price":4761,"PMH":51,"TEU":275,"EDCGAS":0,"simulated":false},{"date":"2024-02-25T12:00:00.214Z","price":4704,"PMH":51,"TEU":275,"EDCGAS":0,"simulated":false},{"date":"2024-02-25T13:00:00.215Z","price":4709,"PMH":51,"TEU":275,"EDCGAS":0,"simulated":false},{"date":"2024-02-25T14:00:00.215Z","price":4847,"PMH":-1,"TEU":275,"EDCGAS":0,"simulated":false},{"date":"2024-02-25T15:00:00.216Z","price":4797,"PMH":1,"TEU":275,"EDCGAS":0,"simulated":false},{"date":"2024-02-25T16:00:00.218Z","price":5023,"PMH":282,"TEU":275,"EDCGAS":0,"simulated":false},{"date":"2024-02-25T17:00:00.219Z","price":4270,"PMH":403,"TEU":275,"EDCGAS":0,"simulated":false},{"date":"2024-02-25T18:00:00.220Z","price":4380,"PMH":585,"TEU":275,"EDCGAS":0,"simulated":false},{"date":"2024-02-25T19:00:00.221Z","price":4607,"PMH":849,"TEU":275,"EDCGAS":0,"simulated":false},{"date":"2024-02-25T20:00:00.222Z","price":4747,"PMH":872,"TEU":275,"EDCGAS":0,"simulated":false},{"date":"2024-02-25T21:00:00.223Z","price":4543,"PMH":609,"TEU":275,"EDCGAS":0,"simulated":false},{"date":"2024-02-25T22:00:00.224Z","price":4425,"PMH":390,"TEU":275,"EDCGAS":0,"simulated":false}]