[{"date":"2025-01-01T23:00:00.776Z","price":16777,"PMH":16746,"TEU":227,"EDCGAS":0,"simulated":false},{"date":"2025-01-02T00:00:00.778Z","price":15531,"PMH":15052,"TEU":227,"EDCGAS":0,"simulated":false},{"date":"2025-01-02T01:00:00.779Z","price":14096,"PMH":12418,"TEU":227,"EDCGAS":0,"simulated":false},{"date":"2025-01-02T02:00:00.780Z","price":14186,"PMH":12391,"TEU":227,"EDCGAS":0,"simulated":false},{"date":"2025-01-02T03:00:00.781Z","price":14185,"PMH":12390,"TEU":227,"EDCGAS":0,"simulated":false},{"date":"2025-01-02T04:00:00.782Z","price":13999,"PMH":12365,"TEU":227,"EDCGAS":0,"simulated":false},{"date":"2025-01-02T05:00:00.783Z","price":16101,"PMH":15538,"TEU":227,"EDCGAS":0,"simulated":false},{"date":"2025-01-02T06:00:00.784Z","price":16746,"PMH":17233,"TEU":227,"EDCGAS":0,"simulated":false},{"date":"2025-01-02T07:00:00.784Z","price":20194,"PMH":18137,"TEU":2820,"EDCGAS":0,"simulated":false},{"date":"2025-01-02T08:00:00.785Z","price":20046,"PMH":17985,"TEU":2820,"EDCGAS":0,"simulated":false},{"date":"2025-01-02T09:00:00.786Z","price":24116,"PMH":15182,"TEU":9254,"EDCGAS":0,"simulated":false},{"date":"2025-01-02T10:00:00.786Z","price":23854,"PMH":14758,"TEU":9254,"EDCGAS":0,"simulated":false},{"date":"2025-01-02T11:00:00.787Z","price":23588,"PMH":14747,"TEU":9254,"EDCGAS":0,"simulated":false},{"date":"2025-01-02T12:00:00.788Z","price":22646,"PMH":13982,"TEU":9254,"EDCGAS":0,"simulated":false},{"date":"2025-01-02T13:00:00.788Z","price":16745,"PMH":14590,"TEU":2820,"EDCGAS":0,"simulated":false},{"date":"2025-01-02T14:00:00.789Z","price":17530,"PMH":15328,"TEU":2820,"EDCGAS":0,"simulated":false},{"date":"2025-01-02T15:00:00.790Z","price":18657,"PMH":16500,"TEU":2820,"EDCGAS":0,"simulated":false},{"date":"2025-01-02T16:00:00.791Z","price":19970,"PMH":18146,"TEU":2820,"EDCGAS":0,"simulated":false},{"date":"2025-01-02T17:00:00.791Z","price":27439,"PMH":18936,"TEU":9254,"EDCGAS":0,"simulated":false},{"date":"2025-01-02T18:00:00.792Z","price":27724,"PMH":19244,"TEU":9254,"EDCGAS":0,"simulated":false},{"date":"2025-01-02T19:00:00.793Z","price":27806,"PMH":19330,"TEU":9254,"EDCGAS":0,"simulated":false},{"date":"2025-01-02T20:00:00.793Z","price":27491,"PMH":19028,"TEU":9254,"EDCGAS":0,"simulated":false},{"date":"2025-01-02T21:00:00.795Z","price":20380,"PMH":18360,"TEU":2820,"EDCGAS":0,"simulated":false},{"date":"2025-01-02T22:00:00.796Z","price":19099,"PMH":16982,"TEU":2820,"EDCGAS":0,"simulated":false}]