[{"date":"2025-10-17T22:00:00.507Z","price":16857,"PMH":14836,"TEU":299,"EDCGAS":0,"simulated":false},{"date":"2025-10-17T23:00:00.510Z","price":15511,"PMH":13397,"TEU":299,"EDCGAS":0,"simulated":false},{"date":"2025-10-18T00:00:00.512Z","price":14175,"PMH":11987,"TEU":299,"EDCGAS":0,"simulated":false},{"date":"2025-10-18T01:00:00.513Z","price":13916,"PMH":12075,"TEU":299,"EDCGAS":0,"simulated":false},{"date":"2025-10-18T02:00:00.514Z","price":14078,"PMH":12217,"TEU":299,"EDCGAS":0,"simulated":false},{"date":"2025-10-18T03:00:00.515Z","price":13521,"PMH":11628,"TEU":299,"EDCGAS":0,"simulated":false},{"date":"2025-10-18T04:00:00.516Z","price":14103,"PMH":12314,"TEU":299,"EDCGAS":0,"simulated":false},{"date":"2025-10-18T05:00:00.517Z","price":15302,"PMH":13441,"TEU":299,"EDCGAS":0,"simulated":false},{"date":"2025-10-18T06:00:00.519Z","price":15637,"PMH":13799,"TEU":299,"EDCGAS":0,"simulated":false},{"date":"2025-10-18T07:00:00.520Z","price":14708,"PMH":11938,"TEU":299,"EDCGAS":0,"simulated":false},{"date":"2025-10-18T08:00:00.522Z","price":11388,"PMH":8340,"TEU":299,"EDCGAS":0,"simulated":false},{"date":"2025-10-18T09:00:00.523Z","price":7359,"PMH":3395,"TEU":299,"EDCGAS":0,"simulated":false},{"date":"2025-10-18T10:00:00.526Z","price":5066,"PMH":808,"TEU":299,"EDCGAS":0,"simulated":false},{"date":"2025-10-18T11:00:00.527Z","price":4733,"PMH":556,"TEU":299,"EDCGAS":0,"simulated":false},{"date":"2025-10-18T12:00:00.528Z","price":4495,"PMH":277,"TEU":299,"EDCGAS":0,"simulated":false},{"date":"2025-10-18T13:00:00.530Z","price":4368,"PMH":122,"TEU":299,"EDCGAS":0,"simulated":false},{"date":"2025-10-18T14:00:00.531Z","price":4835,"PMH":515,"TEU":299,"EDCGAS":0,"simulated":false},{"date":"2025-10-18T15:00:00.532Z","price":9173,"PMH":5406,"TEU":299,"EDCGAS":0,"simulated":false},{"date":"2025-10-18T16:00:00.533Z","price":14044,"PMH":11061,"TEU":299,"EDCGAS":0,"simulated":false},{"date":"2025-10-18T17:00:00.534Z","price":15249,"PMH":13813,"TEU":299,"EDCGAS":0,"simulated":false},{"date":"2025-10-18T18:00:00.535Z","price":16193,"PMH":15024,"TEU":299,"EDCGAS":0,"simulated":false},{"date":"2025-10-18T19:00:00.537Z","price":15496,"PMH":14134,"TEU":299,"EDCGAS":0,"simulated":false},{"date":"2025-10-18T20:00:00.538Z","price":14653,"PMH":13274,"TEU":299,"EDCGAS":0,"simulated":false},{"date":"2025-10-18T21:00:00.544Z","price":14390,"PMH":12832,"TEU":299,"EDCGAS":0,"simulated":false}]