[{"date":"2025-09-18T22:00:00.573Z","price":14421,"PMH":13211,"TEU":299,"EDCGAS":0,"simulated":false},{"date":"2025-09-18T23:00:00.576Z","price":14272,"PMH":13026,"TEU":299,"EDCGAS":0,"simulated":false},{"date":"2025-09-19T00:00:00.577Z","price":14068,"PMH":12748,"TEU":299,"EDCGAS":0,"simulated":false},{"date":"2025-09-19T01:00:00.578Z","price":13763,"PMH":12769,"TEU":299,"EDCGAS":0,"simulated":false},{"date":"2025-09-19T02:00:00.579Z","price":13644,"PMH":12642,"TEU":299,"EDCGAS":0,"simulated":false},{"date":"2025-09-19T03:00:00.580Z","price":13674,"PMH":12692,"TEU":299,"EDCGAS":0,"simulated":false},{"date":"2025-09-19T04:00:00.581Z","price":13990,"PMH":12879,"TEU":299,"EDCGAS":0,"simulated":false},{"date":"2025-09-19T05:00:00.582Z","price":14829,"PMH":13838,"TEU":299,"EDCGAS":0,"simulated":false},{"date":"2025-09-19T06:00:00.583Z","price":16672,"PMH":13088,"TEU":2820,"EDCGAS":0,"simulated":false},{"date":"2025-09-19T07:00:00.584Z","price":16429,"PMH":12235,"TEU":2820,"EDCGAS":0,"simulated":false},{"date":"2025-09-19T08:00:00.586Z","price":18242,"PMH":7595,"TEU":9254,"EDCGAS":0,"simulated":false},{"date":"2025-09-19T09:00:00.587Z","price":16512,"PMH":5891,"TEU":9254,"EDCGAS":0,"simulated":false},{"date":"2025-09-19T10:00:00.589Z","price":16125,"PMH":5521,"TEU":9254,"EDCGAS":0,"simulated":false},{"date":"2025-09-19T11:00:00.593Z","price":15471,"PMH":5067,"TEU":9254,"EDCGAS":0,"simulated":false},{"date":"2025-09-19T12:00:00.594Z","price":7462,"PMH":3503,"TEU":2820,"EDCGAS":0,"simulated":false},{"date":"2025-09-19T13:00:00.595Z","price":7648,"PMH":3692,"TEU":2820,"EDCGAS":0,"simulated":false},{"date":"2025-09-19T14:00:00.596Z","price":10104,"PMH":6231,"TEU":2820,"EDCGAS":0,"simulated":false},{"date":"2025-09-19T15:00:00.597Z","price":11751,"PMH":7619,"TEU":2820,"EDCGAS":0,"simulated":false},{"date":"2025-09-19T16:00:00.598Z","price":19428,"PMH":8927,"TEU":9254,"EDCGAS":0,"simulated":false},{"date":"2025-09-19T17:00:00.599Z","price":23263,"PMH":12587,"TEU":9254,"EDCGAS":0,"simulated":false},{"date":"2025-09-19T18:00:00.600Z","price":24804,"PMH":14478,"TEU":9254,"EDCGAS":0,"simulated":false},{"date":"2025-09-19T19:00:00.602Z","price":24680,"PMH":14469,"TEU":9254,"EDCGAS":0,"simulated":false},{"date":"2025-09-19T20:00:00.603Z","price":16190,"PMH":12319,"TEU":2820,"EDCGAS":0,"simulated":false},{"date":"2025-09-19T21:00:00.604Z","price":16265,"PMH":12230,"TEU":2820,"EDCGAS":0,"simulated":false}]