[{"date":"2026-03-10T23:00:00.835Z","price":17059,"PMH":16989,"TEU":329,"EDCGAS":0,"simulated":false},{"date":"2026-03-11T00:00:00.138Z","price":15461,"PMH":15108,"TEU":329,"EDCGAS":0,"simulated":false},{"date":"2026-03-11T01:00:00.139Z","price":14697,"PMH":14756,"TEU":329,"EDCGAS":0,"simulated":false},{"date":"2026-03-11T02:00:00.142Z","price":13837,"PMH":13753,"TEU":329,"EDCGAS":0,"simulated":false},{"date":"2026-03-11T03:00:00.144Z","price":14236,"PMH":14221,"TEU":329,"EDCGAS":0,"simulated":false},{"date":"2026-03-11T04:00:00.147Z","price":15468,"PMH":15000,"TEU":329,"EDCGAS":0,"simulated":false},{"date":"2026-03-11T05:00:00.150Z","price":17728,"PMH":15454,"TEU":329,"EDCGAS":0,"simulated":false},{"date":"2026-03-11T06:00:00.152Z","price":20085,"PMH":16941,"TEU":329,"EDCGAS":0,"simulated":false},{"date":"2026-03-11T07:00:00.153Z","price":20277,"PMH":14482,"TEU":2927,"EDCGAS":0,"simulated":false},{"date":"2026-03-11T08:00:00.155Z","price":11622,"PMH":8164,"TEU":2927,"EDCGAS":0,"simulated":false},{"date":"2026-03-11T09:00:00.157Z","price":14103,"PMH":3718,"TEU":9755,"EDCGAS":0,"simulated":false},{"date":"2026-03-11T10:00:00.159Z","price":12671,"PMH":2289,"TEU":9755,"EDCGAS":0,"simulated":false},{"date":"2026-03-11T11:00:00.160Z","price":12105,"PMH":1738,"TEU":9755,"EDCGAS":0,"simulated":false},{"date":"2026-03-11T12:00:00.162Z","price":12996,"PMH":2617,"TEU":9755,"EDCGAS":0,"simulated":false},{"date":"2026-03-11T13:00:00.167Z","price":7250,"PMH":3844,"TEU":2927,"EDCGAS":0,"simulated":false},{"date":"2026-03-11T14:00:00.169Z","price":8004,"PMH":4607,"TEU":2927,"EDCGAS":0,"simulated":false},{"date":"2026-03-11T15:00:00.172Z","price":9656,"PMH":6269,"TEU":2927,"EDCGAS":0,"simulated":false},{"date":"2026-03-11T16:00:00.174Z","price":14641,"PMH":10422,"TEU":2927,"EDCGAS":0,"simulated":false},{"date":"2026-03-11T17:00:00.176Z","price":27685,"PMH":15171,"TEU":9755,"EDCGAS":0,"simulated":false},{"date":"2026-03-11T18:00:00.178Z","price":32066,"PMH":19323,"TEU":9755,"EDCGAS":0,"simulated":false},{"date":"2026-03-11T19:00:00.180Z","price":39858,"PMH":28038,"TEU":9755,"EDCGAS":0,"simulated":false},{"date":"2026-03-11T20:00:00.182Z","price":32778,"PMH":20322,"TEU":9755,"EDCGAS":0,"simulated":false},{"date":"2026-03-11T21:00:00.184Z","price":22280,"PMH":17736,"TEU":2927,"EDCGAS":0,"simulated":false},{"date":"2026-03-11T22:00:00.186Z","price":20292,"PMH":16141,"TEU":2927,"EDCGAS":0,"simulated":false}]