[{"date":"2026-05-30T22:00:00.464Z","price":14768,"PMH":11876,"TEU":329,"EDCGAS":0,"simulated":false},{"date":"2026-05-30T23:00:00.685Z","price":14177,"PMH":11086,"TEU":329,"EDCGAS":0,"simulated":false},{"date":"2026-05-31T00:00:00.686Z","price":12949,"PMH":9529,"TEU":329,"EDCGAS":0,"simulated":false},{"date":"2026-05-31T01:00:00.686Z","price":13311,"PMH":9889,"TEU":329,"EDCGAS":0,"simulated":false},{"date":"2026-05-31T02:00:00.687Z","price":12376,"PMH":8748,"TEU":329,"EDCGAS":0,"simulated":false},{"date":"2026-05-31T03:00:00.688Z","price":12389,"PMH":8759,"TEU":329,"EDCGAS":0,"simulated":false},{"date":"2026-05-31T04:00:00.689Z","price":13235,"PMH":9680,"TEU":329,"EDCGAS":0,"simulated":false},{"date":"2026-05-31T05:00:00.690Z","price":12674,"PMH":8187,"TEU":329,"EDCGAS":0,"simulated":false},{"date":"2026-05-31T06:00:00.691Z","price":6228,"PMH":2291,"TEU":329,"EDCGAS":0,"simulated":false},{"date":"2026-05-31T07:00:00.692Z","price":3360,"PMH":254,"TEU":329,"EDCGAS":0,"simulated":false},{"date":"2026-05-31T08:00:00.693Z","price":3690,"PMH":0,"TEU":329,"EDCGAS":0,"simulated":false},{"date":"2026-05-31T09:00:00.693Z","price":3643,"PMH":0,"TEU":329,"EDCGAS":0,"simulated":false},{"date":"2026-05-31T10:00:00.696Z","price":3713,"PMH":2,"TEU":329,"EDCGAS":0,"simulated":false},{"date":"2026-05-31T11:00:00.697Z","price":3585,"PMH":0,"TEU":329,"EDCGAS":0,"simulated":false},{"date":"2026-05-31T12:00:00.697Z","price":4010,"PMH":-2,"TEU":329,"EDCGAS":0,"simulated":false},{"date":"2026-05-31T13:00:00.698Z","price":4109,"PMH":-39,"TEU":329,"EDCGAS":0,"simulated":false},{"date":"2026-05-31T14:00:00.699Z","price":4178,"PMH":-2,"TEU":329,"EDCGAS":0,"simulated":false},{"date":"2026-05-31T15:00:00.700Z","price":4259,"PMH":0,"TEU":329,"EDCGAS":0,"simulated":false},{"date":"2026-05-31T16:00:00.701Z","price":4123,"PMH":462,"TEU":329,"EDCGAS":0,"simulated":false},{"date":"2026-05-31T17:00:00.702Z","price":7219,"PMH":3577,"TEU":329,"EDCGAS":0,"simulated":false},{"date":"2026-05-31T18:00:00.703Z","price":11360,"PMH":7725,"TEU":329,"EDCGAS":0,"simulated":false},{"date":"2026-05-31T19:00:00.704Z","price":15055,"PMH":11621,"TEU":329,"EDCGAS":0,"simulated":false},{"date":"2026-05-31T20:00:00.704Z","price":15391,"PMH":11973,"TEU":329,"EDCGAS":0,"simulated":false},{"date":"2026-05-31T21:00:00.706Z","price":13813,"PMH":10872,"TEU":329,"EDCGAS":0,"simulated":false}]