[{"date":"2026-06-30T22:00:00.026Z","price":16993,"PMH":13772,"TEU":329,"EDCGAS":0,"simulated":false},{"date":"2026-06-30T23:00:00.404Z","price":17037,"PMH":14049,"TEU":329,"EDCGAS":0,"simulated":false},{"date":"2026-07-01T00:00:00.405Z","price":15653,"PMH":12925,"TEU":329,"EDCGAS":0,"simulated":false},{"date":"2026-07-01T01:00:00.406Z","price":14453,"PMH":11659,"TEU":329,"EDCGAS":0,"simulated":false},{"date":"2026-07-01T02:00:00.407Z","price":13802,"PMH":10922,"TEU":329,"EDCGAS":0,"simulated":false},{"date":"2026-07-01T03:00:00.410Z","price":14284,"PMH":11417,"TEU":329,"EDCGAS":0,"simulated":false},{"date":"2026-07-01T04:00:00.411Z","price":16268,"PMH":13080,"TEU":329,"EDCGAS":0,"simulated":false},{"date":"2026-07-01T05:00:00.415Z","price":16761,"PMH":13313,"TEU":329,"EDCGAS":0,"simulated":false},{"date":"2026-07-01T06:00:00.417Z","price":13705,"PMH":7280,"TEU":2927,"EDCGAS":0,"simulated":false},{"date":"2026-07-01T07:00:00.417Z","price":7786,"PMH":1064,"TEU":2927,"EDCGAS":0,"simulated":false},{"date":"2026-07-01T08:00:00.419Z","price":13935,"PMH":164,"TEU":9755,"EDCGAS":0,"simulated":false},{"date":"2026-07-01T09:00:00.419Z","price":13719,"PMH":17,"TEU":9755,"EDCGAS":0,"simulated":false},{"date":"2026-07-01T10:00:00.420Z","price":13712,"PMH":17,"TEU":9755,"EDCGAS":0,"simulated":false},{"date":"2026-07-01T11:00:00.421Z","price":13702,"PMH":26,"TEU":9755,"EDCGAS":0,"simulated":false},{"date":"2026-07-01T12:00:00.422Z","price":6687,"PMH":15,"TEU":2927,"EDCGAS":0,"simulated":false},{"date":"2026-07-01T13:00:00.423Z","price":6566,"PMH":2,"TEU":2927,"EDCGAS":0,"simulated":false},{"date":"2026-07-01T14:00:00.424Z","price":6501,"PMH":9,"TEU":2927,"EDCGAS":0,"simulated":false},{"date":"2026-07-01T15:00:00.425Z","price":6497,"PMH":74,"TEU":2927,"EDCGAS":0,"simulated":false},{"date":"2026-07-01T16:00:00.425Z","price":13499,"PMH":170,"TEU":9755,"EDCGAS":0,"simulated":false},{"date":"2026-07-01T17:00:00.426Z","price":16000,"PMH":2442,"TEU":9755,"EDCGAS":0,"simulated":false},{"date":"2026-07-01T18:00:00.427Z","price":21875,"PMH":8668,"TEU":9755,"EDCGAS":0,"simulated":false},{"date":"2026-07-01T19:00:00.428Z","price":25626,"PMH":12910,"TEU":9755,"EDCGAS":0,"simulated":false},{"date":"2026-07-01T20:00:00.429Z","price":18608,"PMH":12833,"TEU":2927,"EDCGAS":0,"simulated":false},{"date":"2026-07-01T21:00:00.430Z","price":16288,"PMH":10392,"TEU":2927,"EDCGAS":0,"simulated":false}]