{"pvpc":{"prices":{"nextPrices":[{"price":8561,"date":"2026-03-20T13:00:00.385Z","simulated":false},{"price":8754,"date":"2026-03-20T14:00:00.386Z","simulated":false},{"price":9796,"date":"2026-03-20T15:00:00.387Z","simulated":false},{"price":13033,"date":"2026-03-20T16:00:00.388Z","simulated":false},{"price":24084,"date":"2026-03-20T17:00:00.389Z","simulated":false},{"price":28095,"date":"2026-03-20T18:00:00.390Z","simulated":false},{"price":27663,"date":"2026-03-20T19:00:00.391Z","simulated":false},{"price":25874,"date":"2026-03-20T20:00:00.392Z","simulated":false},{"price":18902,"date":"2026-03-20T21:00:00.393Z","simulated":false},{"price":17891,"date":"2026-03-20T22:00:00.394Z","simulated":false}],"devices":[{"id":"generic1","duration":"1","consumptionKWh":"1","isOutOfRange":false,"startTime":"2026-03-20T13:00:00+00:00","endTime":"2026-03-20T14:00:00+00:00","currentCost":"0.086","cheapestCost":"0.086","costSavings":0},{"id":"generic2","duration":"2","consumptionKWh":"1","isOutOfRange":false,"startTime":"2026-03-20T13:00:00+00:00","endTime":"2026-03-20T15:00:00+00:00","currentCost":"0.17","cheapestCost":"0.17","costSavings":0},{"id":"generic3","duration":"3","consumptionKWh":"1","isOutOfRange":false,"startTime":"2026-03-20T13:00:00+00:00","endTime":"2026-03-20T16:00:00+00:00","currentCost":"0.27","cheapestCost":"0.27","costSavings":0},{"id":"generic4","duration":"4","consumptionKWh":"1","isOutOfRange":false,"startTime":"2026-03-20T13:00:00+00:00","endTime":"2026-03-20T17:00:00+00:00","currentCost":"0.40","cheapestCost":"0.40","costSavings":0},{"id":"generic5","duration":"5","consumptionKWh":"1","isOutOfRange":false,"startTime":"2026-03-20T13:00:00+00:00","endTime":"2026-03-20T18:00:00+00:00","currentCost":"0.64","cheapestCost":"0.64","costSavings":0},{"id":"generic6","duration":"6","consumptionKWh":"1","isOutOfRange":false,"startTime":"2026-03-20T13:00:00+00:00","endTime":"2026-03-20T19:00:00+00:00","currentCost":"0.92","cheapestCost":"0.92","costSavings":0},{"id":"generic7","duration":"7","consumptionKWh":"1","isOutOfRange":false,"startTime":"2026-03-20T13:00:00+00:00","endTime":"2026-03-20T20:00:00+00:00","currentCost":"1.2","cheapestCost":"1.2","costSavings":0},{"id":"generic8","duration":"8","consumptionKWh":"1","isOutOfRange":false,"startTime":"2026-03-20T13:00:00+00:00","endTime":"2026-03-20T21:00:00+00:00","currentCost":"1.5","cheapestCost":"1.5","costSavings":0}],"summary":{"avgPrice":14614,"bestPrice":{"price":8561,"date":"2026-03-20T13:00:00.385Z"},"currentPrice":{"price":8561,"date":"2026-03-20T13:00:00.385Z"},"worstPrice":{"price":28095,"date":"2026-03-20T18:00:00.390Z"}}},"lastUpdated":"2026-03-20 14:02:45"},"pvpcToday":{"avgPrice":14614,"bestPrice":{"date":"2026-03-20T13:00:00.385Z","price":8561,"PMH":263,"TEU":2927,"EDCGAS":0,"simulated":false},"currentPrice":{"date":"2026-03-20T13:00:00.385Z","price":8561,"PMH":263,"TEU":2927,"EDCGAS":0,"simulated":false},"worstPrice":{"date":"2026-03-20T18:00:00.390Z","price":28095,"PMH":11818,"TEU":9755,"EDCGAS":0,"simulated":false}},"pvpcTomorrow":{}}