{"pvpc":{"prices":{"nextPrices":[{"price":13812,"date":"2026-06-02T04:00:00.254Z","simulated":false},{"price":13732,"date":"2026-06-02T05:00:00.254Z","simulated":false},{"price":13490,"date":"2026-06-02T06:00:00.255Z","simulated":false},{"price":8998,"date":"2026-06-02T07:00:00.255Z","simulated":false},{"price":13041,"date":"2026-06-02T08:00:00.256Z","simulated":false},{"price":12772,"date":"2026-06-02T09:00:00.258Z","simulated":false},{"price":12787,"date":"2026-06-02T10:00:00.258Z","simulated":false},{"price":12886,"date":"2026-06-02T11:00:00.259Z","simulated":false},{"price":5991,"date":"2026-06-02T12:00:00.259Z","simulated":false},{"price":6037,"date":"2026-06-02T13:00:00.260Z","simulated":false},{"price":5954,"date":"2026-06-02T14:00:00.261Z","simulated":false},{"price":5842,"date":"2026-06-02T15:00:00.261Z","simulated":false},{"price":12567,"date":"2026-06-02T16:00:00.262Z","simulated":false},{"price":13344,"date":"2026-06-02T17:00:00.263Z","simulated":false},{"price":18677,"date":"2026-06-02T18:00:00.264Z","simulated":false},{"price":23109,"date":"2026-06-02T19:00:00.264Z","simulated":false},{"price":16182,"date":"2026-06-02T20:00:00.265Z","simulated":false},{"price":15259,"date":"2026-06-02T21:00:00.266Z","simulated":false}],"devices":[{"id":"generic1","duration":"1","consumptionKWh":"1","isOutOfRange":false,"startTime":"2026-06-02T15:00:00+00:00","endTime":"2026-06-02T16:00:00+00:00","currentCost":"0.14","cheapestCost":"0.058","costSavings":0.08200000000000002},{"id":"generic2","duration":"2","consumptionKWh":"1","isOutOfRange":false,"startTime":"2026-06-02T14:00:00+00:00","endTime":"2026-06-02T16:00:00+00:00","currentCost":"0.28","cheapestCost":"0.12","costSavings":0.16000000000000003},{"id":"generic3","duration":"3","consumptionKWh":"1","isOutOfRange":false,"startTime":"2026-06-02T13:00:00+00:00","endTime":"2026-06-02T16:00:00+00:00","currentCost":"0.41","cheapestCost":"0.18","costSavings":0.22999999999999998},{"id":"generic4","duration":"4","consumptionKWh":"1","isOutOfRange":false,"startTime":"2026-06-02T12:00:00+00:00","endTime":"2026-06-02T16:00:00+00:00","currentCost":"0.50","cheapestCost":"0.24","costSavings":0.26},{"id":"generic5","duration":"5","consumptionKWh":"1","isOutOfRange":false,"startTime":"2026-06-02T12:00:00+00:00","endTime":"2026-06-02T17:00:00+00:00","currentCost":"0.63","cheapestCost":"0.36","costSavings":0.27},{"id":"generic6","duration":"6","consumptionKWh":"1","isOutOfRange":false,"startTime":"2026-06-02T11:00:00+00:00","endTime":"2026-06-02T17:00:00+00:00","currentCost":"0.76","cheapestCost":"0.49","costSavings":0.27},{"id":"generic7","duration":"7","consumptionKWh":"1","isOutOfRange":false,"startTime":"2026-06-02T10:00:00+00:00","endTime":"2026-06-02T17:00:00+00:00","currentCost":"0.89","cheapestCost":"0.62","costSavings":0.27},{"id":"generic8","duration":"8","consumptionKWh":"1","isOutOfRange":false,"startTime":"2026-06-02T09:00:00+00:00","endTime":"2026-06-02T17:00:00+00:00","currentCost":"1.0","cheapestCost":"0.75","costSavings":0.25}],"summary":{"avgPrice":12875,"bestPrice":{"price":5842,"date":"2026-06-02T15:00:00.261Z"},"currentPrice":{"price":13812,"date":"2026-06-02T04:00:00.254Z"},"worstPrice":{"price":23109,"date":"2026-06-02T19:00:00.264Z"}}},"lastUpdated":"2026-06-02 06:24:40"},"pvpcToday":{"avgPrice":12875,"bestPrice":{"date":"2026-06-02T15:00:00.261Z","price":5842,"PMH":-1,"TEU":2927,"EDCGAS":0,"simulated":false},"currentPrice":{"date":"2026-06-02T04:00:00.254Z","price":13812,"PMH":11399,"TEU":329,"EDCGAS":0,"simulated":false},"worstPrice":{"date":"2026-06-02T19:00:00.264Z","price":23109,"PMH":10756,"TEU":9755,"EDCGAS":0,"simulated":false}},"pvpcTomorrow":{}}