{"omie":{"prices":{"nextPrices":[{"price":8542,"date":"2026-03-08T13:00:00+01:00"},{"price":8522,"date":"2026-03-08T14:00:00+01:00"},{"price":8542,"date":"2026-03-08T15:00:00+01:00"},{"price":8501,"date":"2026-03-08T16:00:00+01:00"},{"price":8211,"date":"2026-03-08T17:00:00+01:00"},{"price":8259,"date":"2026-03-08T18:00:00+01:00"},{"price":8200,"date":"2026-03-08T19:00:00+01:00"},{"price":8400,"date":"2026-03-08T20:00:00+01:00"},{"price":8501,"date":"2026-03-08T21:00:00+01:00"},{"price":8590,"date":"2026-03-08T22:00:00+01:00"},{"price":8391,"date":"2026-03-08T23:00:00+01:00"}],"devices":[{"id":"generic1","duration":"1","consumptionKWh":"1","isOutOfRange":false,"startTime":"2026-03-08T18:00:00+00:00","endTime":"2026-03-08T19:00:00+00:00","currentCost":"0.085","cheapestCost":"0.082","costSavings":0.0030000000000000027},{"id":"generic2","duration":"2","consumptionKWh":"1","isOutOfRange":false,"startTime":"2026-03-08T17:00:00+00:00","endTime":"2026-03-08T19:00:00+00:00","currentCost":"0.17","cheapestCost":"0.16","costSavings":0.010000000000000009},{"id":"generic3","duration":"3","consumptionKWh":"1","isOutOfRange":false,"startTime":"2026-03-08T16:00:00+00:00","endTime":"2026-03-08T19:00:00+00:00","currentCost":"0.26","cheapestCost":"0.25","costSavings":0.010000000000000009},{"id":"generic4","duration":"4","consumptionKWh":"1","isOutOfRange":false,"startTime":"2026-03-08T16:00:00+00:00","endTime":"2026-03-08T20:00:00+00:00","currentCost":"0.34","cheapestCost":"0.33","costSavings":0.010000000000000009},{"id":"generic5","duration":"5","consumptionKWh":"1","isOutOfRange":false,"startTime":"2026-03-08T15:00:00+00:00","endTime":"2026-03-08T20:00:00+00:00","currentCost":"0.42","cheapestCost":"0.42","costSavings":0},{"id":"generic6","duration":"6","consumptionKWh":"1","isOutOfRange":false,"startTime":"2026-03-08T15:00:00+00:00","endTime":"2026-03-08T21:00:00+00:00","currentCost":"0.51","cheapestCost":"0.50","costSavings":0.010000000000000009},{"id":"generic7","duration":"7","consumptionKWh":"1","isOutOfRange":false,"startTime":"2026-03-08T16:00:00+00:00","endTime":"2026-03-08T23:00:00+00:00","currentCost":"0.59","cheapestCost":"0.59","costSavings":0},{"id":"generic8","duration":"8","consumptionKWh":"1","isOutOfRange":false,"startTime":"2026-03-08T15:00:00+00:00","endTime":"2026-03-08T23:00:00+00:00","currentCost":"0.67","cheapestCost":"0.67","costSavings":0}],"summary":{"avgPrice":9180,"bestPrice":{"price":8200,"date":"2026-03-08T19:00:00+01:00"},"currentPrice":{"price":8542,"date":"2026-03-08T13:00:00+01:00"},"worstPrice":{"price":8590,"date":"2026-03-08T22:00:00+01:00"}}},"lastUpdated":"2026-03-08 13:25:01"}}