{"omie":{"nextPrices":[{"price":4001,"date":"2025-06-02T09:00:00+02:00"},{"price":1755,"date":"2025-06-02T10:00:00+02:00"},{"price":295,"date":"2025-06-02T11:00:00+02:00"},{"price":85,"date":"2025-06-02T12:00:00+02:00"},{"price":46,"date":"2025-06-02T13:00:00+02:00"},{"price":0,"date":"2025-06-02T14:00:00+02:00"},{"price":0,"date":"2025-06-02T15:00:00+02:00"},{"price":0,"date":"2025-06-02T16:00:00+02:00"},{"price":172,"date":"2025-06-02T17:00:00+02:00"},{"price":1490,"date":"2025-06-02T18:00:00+02:00"},{"price":4029,"date":"2025-06-02T19:00:00+02:00"},{"price":8805,"date":"2025-06-02T20:00:00+02:00"},{"price":10000,"date":"2025-06-02T21:00:00+02:00"},{"price":9821,"date":"2025-06-02T22:00:00+02:00"},{"price":6650,"date":"2025-06-02T23:00:00+02:00"}],"devices":[{"id":"generic1","duration":"1","consumptionKWh":"1","isOutOfRange":false,"startTime":"2025-06-02T12:00:00+00:00","endTime":"2025-06-02T13:00:00+00:00","currentCost":"0.040","cheapestCost":"0.0","costSavings":0.04},{"id":"generic2","duration":"2","consumptionKWh":"1","isOutOfRange":false,"startTime":"2025-06-02T12:00:00+00:00","endTime":"2025-06-02T14:00:00+00:00","currentCost":"0.058","cheapestCost":"0.0","costSavings":0.058},{"id":"generic3","duration":"3","consumptionKWh":"1","isOutOfRange":false,"startTime":"2025-06-02T12:00:00+00:00","endTime":"2025-06-02T15:00:00+00:00","currentCost":"0.061","cheapestCost":"0.0","costSavings":0.061},{"id":"generic4","duration":"4","consumptionKWh":"1","isOutOfRange":false,"startTime":"2025-06-02T11:00:00+00:00","endTime":"2025-06-02T15:00:00+00:00","currentCost":"0.061","cheapestCost":"0.00046","costSavings":0.06054},{"id":"generic5","duration":"5","consumptionKWh":"1","isOutOfRange":false,"startTime":"2025-06-02T10:00:00+00:00","endTime":"2025-06-02T15:00:00+00:00","currentCost":"0.062","cheapestCost":"0.0013","costSavings":0.0607},{"id":"generic6","duration":"6","consumptionKWh":"1","isOutOfRange":false,"startTime":"2025-06-02T10:00:00+00:00","endTime":"2025-06-02T16:00:00+00:00","currentCost":"0.062","cheapestCost":"0.0030","costSavings":0.059},{"id":"generic7","duration":"7","consumptionKWh":"1","isOutOfRange":false,"startTime":"2025-06-02T09:00:00+00:00","endTime":"2025-06-02T16:00:00+00:00","currentCost":"0.062","cheapestCost":"0.0060","costSavings":0.056},{"id":"generic8","duration":"8","consumptionKWh":"1","isOutOfRange":false,"startTime":"2025-06-02T09:00:00+00:00","endTime":"2025-06-02T17:00:00+00:00","currentCost":"0.062","cheapestCost":"0.021","costSavings":0.040999999999999995}],"summary":{"avgPrice":3113,"bestPrice":{"price":0,"date":"2025-06-02T14:00:00+02:00"},"currentPrice":{"price":4001,"date":"2025-06-02T09:00:00+02:00"},"worstPrice":{"price":10000,"date":"2025-06-02T21:00:00+02:00"}}},"pvpc":{"nextPrices":[{"price":12081,"date":"2025-06-02T07:00:00.349Z","simulated":false},{"price":16219,"date":"2025-06-02T08:00:00.350Z","simulated":false},{"price":14632,"date":"2025-06-02T09:00:00.351Z","simulated":false},{"price":14388,"date":"2025-06-02T10:00:00.354Z","simulated":false},{"price":14050,"date":"2025-06-02T11:00:00.355Z","simulated":false},{"price":7502,"date":"2025-06-02T12:00:00.355Z","simulated":false},{"price":7564,"date":"2025-06-02T13:00:00.356Z","simulated":false},{"price":7590,"date":"2025-06-02T14:00:00.357Z","simulated":false},{"price":7770,"date":"2025-06-02T15:00:00.358Z","simulated":false},{"price":16072,"date":"2025-06-02T16:00:00.359Z","simulated":false},{"price":18647,"date":"2025-06-02T17:00:00.360Z","simulated":false},{"price":23584,"date":"2025-06-02T18:00:00.361Z","simulated":false},{"price":24579,"date":"2025-06-02T19:00:00.362Z","simulated":false},{"price":17934,"date":"2025-06-02T20:00:00.363Z","simulated":false},{"price":14791,"date":"2025-06-02T21:00:00.364Z","simulated":false}],"devices":[{"id":"generic1","duration":"1","consumptionKWh":"1","isOutOfRange":false,"startTime":"2025-06-02T12:00:00+00:00","endTime":"2025-06-02T13:00:00+00:00","currentCost":"0.12","cheapestCost":"0.075","costSavings":0.045},{"id":"generic2","duration":"2","consumptionKWh":"1","isOutOfRange":false,"startTime":"2025-06-02T12:00:00+00:00","endTime":"2025-06-02T14:00:00+00:00","currentCost":"0.28","cheapestCost":"0.15","costSavings":0.13000000000000003},{"id":"generic3","duration":"3","consumptionKWh":"1","isOutOfRange":false,"startTime":"2025-06-02T12:00:00+00:00","endTime":"2025-06-02T15:00:00+00:00","currentCost":"0.43","cheapestCost":"0.23","costSavings":0.19999999999999998},{"id":"generic4","duration":"4","consumptionKWh":"1","isOutOfRange":false,"startTime":"2025-06-02T12:00:00+00:00","endTime":"2025-06-02T16:00:00+00:00","currentCost":"0.57","cheapestCost":"0.30","costSavings":0.26999999999999996},{"id":"generic5","duration":"5","consumptionKWh":"1","isOutOfRange":false,"startTime":"2025-06-02T11:00:00+00:00","endTime":"2025-06-02T16:00:00+00:00","currentCost":"0.71","cheapestCost":"0.44","costSavings":0.26999999999999996},{"id":"generic6","duration":"6","consumptionKWh":"1","isOutOfRange":false,"startTime":"2025-06-02T10:00:00+00:00","endTime":"2025-06-02T16:00:00+00:00","currentCost":"0.79","cheapestCost":"0.59","costSavings":0.20000000000000007},{"id":"generic7","duration":"7","consumptionKWh":"1","isOutOfRange":false,"startTime":"2025-06-02T09:00:00+00:00","endTime":"2025-06-02T16:00:00+00:00","currentCost":"0.86","cheapestCost":"0.73","costSavings":0.13},{"id":"generic8","duration":"8","consumptionKWh":"1","isOutOfRange":false,"startTime":"2025-06-02T09:00:00+00:00","endTime":"2025-06-02T17:00:00+00:00","currentCost":"0.94","cheapestCost":"0.90","costSavings":0.039999999999999925}],"summary":{"avgPrice":12708,"bestPrice":{"price":7502,"date":"2025-06-02T12:00:00.355Z"},"currentPrice":{"price":12081,"date":"2025-06-02T07:00:00.349Z"},"worstPrice":{"price":24579,"date":"2025-06-02T19:00:00.362Z"}}},"pvpcToday":{"avgPrice":12708,"bestPrice":{"date":"2025-06-02T12:00:00.355Z","price":7502,"PMH":5,"TEU":2820,"EDCGAS":0,"simulated":false},"currentPrice":{"date":"2025-06-02T07:00:00.349Z","price":12081,"PMH":4592,"TEU":2820,"EDCGAS":0,"simulated":false},"worstPrice":{"date":"2025-06-02T19:00:00.362Z","price":24579,"PMH":11621,"TEU":9254,"EDCGAS":0,"simulated":false}},"pvpcTomorrow":{}}