{"omie":{"nextPrices":[{"price":8095,"date":"2023-04-26T15:00:00+02:00"},{"price":7947,"date":"2023-04-26T16:00:00+02:00"},{"price":8300,"date":"2023-04-26T17:00:00+02:00"},{"price":8704,"date":"2023-04-26T18:00:00+02:00"},{"price":12201,"date":"2023-04-26T19:00:00+02:00"},{"price":13529,"date":"2023-04-26T20:00:00+02:00"},{"price":14612,"date":"2023-04-26T21:00:00+02:00"},{"price":13354,"date":"2023-04-26T22:00:00+02:00"},{"price":12048,"date":"2023-04-26T23:00:00+02:00"},{"price":11369,"date":"2023-04-27T00:00:00+02:00"},{"price":11369,"date":"2023-04-27T01:00:00+02:00"},{"price":10500,"date":"2023-04-27T02:00:00+02:00"},{"price":10000,"date":"2023-04-27T03:00:00+02:00"},{"price":10500,"date":"2023-04-27T04:00:00+02:00"},{"price":10680,"date":"2023-04-27T05:00:00+02:00"},{"price":12339,"date":"2023-04-27T06:00:00+02:00"},{"price":14258,"date":"2023-04-27T07:00:00+02:00"},{"price":13541,"date":"2023-04-27T08:00:00+02:00"},{"price":11318,"date":"2023-04-27T09:00:00+02:00"},{"price":9699,"date":"2023-04-27T10:00:00+02:00"},{"price":9250,"date":"2023-04-27T11:00:00+02:00"},{"price":9400,"date":"2023-04-27T12:00:00+02:00"},{"price":9100,"date":"2023-04-27T13:00:00+02:00"},{"price":8874,"date":"2023-04-27T14:00:00+02:00"},{"price":8648,"date":"2023-04-27T15:00:00+02:00"},{"price":8648,"date":"2023-04-27T16:00:00+02:00"},{"price":9112,"date":"2023-04-27T17:00:00+02:00"},{"price":9999,"date":"2023-04-27T18:00:00+02:00"},{"price":11735,"date":"2023-04-27T19:00:00+02:00"},{"price":12980,"date":"2023-04-27T20:00:00+02:00"},{"price":13801,"date":"2023-04-27T21:00:00+02:00"},{"price":12600,"date":"2023-04-27T22:00:00+02:00"},{"price":12000,"date":"2023-04-27T23:00:00+02:00"}],"devices":[{"id":"generic1","duration":"1","consumptionKWh":"1","isOutOfRange":false,"startTime":"2023-04-26T14:00:00+00:00","endTime":"2023-04-26T15:00:00+00:00","currentCost":"0.081","cheapestCost":"0.079","costSavings":0.0020000000000000018},{"id":"generic2","duration":"2","consumptionKWh":"1","isOutOfRange":false,"startTime":"2023-04-26T13:00:00+00:00","endTime":"2023-04-26T15:00:00+00:00","currentCost":"0.16","cheapestCost":"0.16","costSavings":0},{"id":"generic3","duration":"3","consumptionKWh":"1","isOutOfRange":false,"startTime":"2023-04-26T13:00:00+00:00","endTime":"2023-04-26T16:00:00+00:00","currentCost":"0.24","cheapestCost":"0.24","costSavings":0},{"id":"generic4","duration":"4","consumptionKWh":"1","isOutOfRange":false,"startTime":"2023-04-26T13:00:00+00:00","endTime":"2023-04-26T17:00:00+00:00","currentCost":"0.33","cheapestCost":"0.33","costSavings":0},{"id":"generic5","duration":"5","consumptionKWh":"1","isOutOfRange":false,"startTime":"2023-04-27T11:00:00+00:00","endTime":"2023-04-27T16:00:00+00:00","currentCost":"0.45","cheapestCost":"0.44","costSavings":0.010000000000000009},{"id":"generic6","duration":"6","consumptionKWh":"1","isOutOfRange":false,"startTime":"2023-04-27T10:00:00+00:00","endTime":"2023-04-27T16:00:00+00:00","currentCost":"0.59","cheapestCost":"0.54","costSavings":0.04999999999999993},{"id":"generic7","duration":"7","consumptionKWh":"1","isOutOfRange":false,"startTime":"2023-04-27T09:00:00+00:00","endTime":"2023-04-27T16:00:00+00:00","currentCost":"0.73","cheapestCost":"0.63","costSavings":0.09999999999999998},{"id":"generic8","duration":"8","consumptionKWh":"1","isOutOfRange":false,"startTime":"2023-04-27T08:00:00+00:00","endTime":"2023-04-27T16:00:00+00:00","currentCost":"0.87","cheapestCost":"0.73","costSavings":0.14}],"summary":{"tendency":"down","avgPrice":10889,"bestPrice":{"price":7947,"date":"2023-04-26T16:00:00+02:00"},"currentPrice":{"price":8095,"date":"2023-04-26T15:00:00+02:00"},"worstPrice":{"price":14612,"date":"2023-04-26T21:00:00+02:00"}}},"pvpc":{"nextPrices":[{"price":14647,"date":"2023-04-26T13:00:00.903Z","simulated":false},{"price":14551,"date":"2023-04-26T14:00:00.903Z","simulated":false},{"price":14960,"date":"2023-04-26T15:00:00.904Z","simulated":false},{"price":19842,"date":"2023-04-26T16:00:00.905Z","simulated":false},{"price":23361,"date":"2023-04-26T17:00:00.906Z","simulated":false},{"price":24890,"date":"2023-04-26T18:00:00.907Z","simulated":false},{"price":26175,"date":"2023-04-26T19:00:00.908Z","simulated":false},{"price":20553,"date":"2023-04-26T20:00:00.909Z","simulated":false},{"price":19143,"date":"2023-04-26T21:00:00.910Z","simulated":false},{"price":15260,"date":"2023-04-27T00:00:00+02:00","simulated":true},{"price":15260,"date":"2023-04-27T01:00:00+02:00","simulated":true},{"price":14388,"date":"2023-04-27T02:00:00+02:00","simulated":true},{"price":13887,"date":"2023-04-27T03:00:00+02:00","simulated":true},{"price":14388,"date":"2023-04-27T04:00:00+02:00","simulated":true},{"price":14569,"date":"2023-04-27T05:00:00+02:00","simulated":true},{"price":16232,"date":"2023-04-27T06:00:00+02:00","simulated":true},{"price":18155,"date":"2023-04-27T07:00:00+02:00","simulated":true},{"price":19973,"date":"2023-04-27T08:00:00+02:00","simulated":true},{"price":17749,"date":"2023-04-27T09:00:00+02:00","simulated":true},{"price":20566,"date":"2023-04-27T10:00:00+02:00","simulated":true},{"price":20116,"date":"2023-04-27T11:00:00+02:00","simulated":true},{"price":20266,"date":"2023-04-27T12:00:00+02:00","simulated":true},{"price":19966,"date":"2023-04-27T13:00:00+02:00","simulated":true},{"price":15298,"date":"2023-04-27T14:00:00+02:00","simulated":true},{"price":15072,"date":"2023-04-27T15:00:00+02:00","simulated":true},{"price":15072,"date":"2023-04-27T16:00:00+02:00","simulated":true},{"price":15537,"date":"2023-04-27T17:00:00+02:00","simulated":true},{"price":20866,"date":"2023-04-27T18:00:00+02:00","simulated":true},{"price":22601,"date":"2023-04-27T19:00:00+02:00","simulated":true},{"price":23853,"date":"2023-04-27T20:00:00+02:00","simulated":true},{"price":24674,"date":"2023-04-27T21:00:00+02:00","simulated":true},{"price":19031,"date":"2023-04-27T22:00:00+02:00","simulated":true},{"price":18430,"date":"2023-04-27T23:00:00+02:00","simulated":true}],"devices":[{"id":"generic1","duration":"1","consumptionKWh":"1","isOutOfRange":false,"startTime":"2023-04-27T01:00:00+00:00","endTime":"2023-04-27T02:00:00+00:00","currentCost":"0.15","cheapestCost":"0.14","costSavings":0.009999999999999981},{"id":"generic2","duration":"2","consumptionKWh":"1","isOutOfRange":false,"startTime":"2023-04-27T00:00:00+00:00","endTime":"2023-04-27T02:00:00+00:00","currentCost":"0.29","cheapestCost":"0.28","costSavings":0.009999999999999953},{"id":"generic3","duration":"3","consumptionKWh":"1","isOutOfRange":false,"startTime":"2023-04-27T00:00:00+00:00","endTime":"2023-04-27T03:00:00+00:00","currentCost":"0.44","cheapestCost":"0.43","costSavings":0.010000000000000009},{"id":"generic4","duration":"4","consumptionKWh":"1","isOutOfRange":false,"startTime":"2023-04-27T00:00:00+00:00","endTime":"2023-04-27T04:00:00+00:00","currentCost":"0.64","cheapestCost":"0.57","costSavings":0.07000000000000006},{"id":"generic5","duration":"5","consumptionKWh":"1","isOutOfRange":false,"startTime":"2023-04-26T23:00:00+00:00","endTime":"2023-04-27T04:00:00+00:00","currentCost":"0.87","cheapestCost":"0.72","costSavings":0.15000000000000002},{"id":"generic6","duration":"6","consumptionKWh":"1","isOutOfRange":false,"startTime":"2023-04-26T22:00:00+00:00","endTime":"2023-04-27T04:00:00+00:00","currentCost":"1.1","cheapestCost":"0.88","costSavings":0.22000000000000008},{"id":"generic7","duration":"7","consumptionKWh":"1","isOutOfRange":false,"startTime":"2023-04-26T22:00:00+00:00","endTime":"2023-04-27T05:00:00+00:00","currentCost":"1.4","cheapestCost":"1.0","costSavings":0.3999999999999999},{"id":"generic8","duration":"8","consumptionKWh":"1","isOutOfRange":false,"startTime":"2023-04-26T22:00:00+00:00","endTime":"2023-04-27T06:00:00+00:00","currentCost":"1.6","cheapestCost":"1.2","costSavings":0.40000000000000013}],"summary":{"tendency":"down","avgPrice":18074,"bestPrice":{"price":13887,"date":"2023-04-27T03:00:00+02:00"},"currentPrice":{"price":14647,"date":"2023-04-26T13:00:00.903Z"},"worstPrice":{"price":26175,"date":"2023-04-26T19:00:00.908Z"}}}}