{"pvpc":{"prices":{"nextPrices":[{"price":5306,"date":"2024-04-22T05:00:00.871Z","simulated":false},{"price":7547,"date":"2024-04-22T06:00:00.872Z","simulated":false},{"price":7447,"date":"2024-04-22T07:00:00.873Z","simulated":false},{"price":12321,"date":"2024-04-22T08:00:00.874Z","simulated":false},{"price":12370,"date":"2024-04-22T09:00:00.875Z","simulated":false},{"price":12414,"date":"2024-04-22T10:00:00.875Z","simulated":false},{"price":12360,"date":"2024-04-22T11:00:00.876Z","simulated":false},{"price":7415,"date":"2024-04-22T12:00:00.877Z","simulated":false},{"price":7465,"date":"2024-04-22T13:00:00.878Z","simulated":false},{"price":7475,"date":"2024-04-22T14:00:00.880Z","simulated":false},{"price":7470,"date":"2024-04-22T15:00:00.881Z","simulated":false},{"price":12253,"date":"2024-04-22T16:00:00.882Z","simulated":false},{"price":12275,"date":"2024-04-22T17:00:00.883Z","simulated":false},{"price":13021,"date":"2024-04-22T18:00:00.884Z","simulated":false},{"price":13741,"date":"2024-04-22T19:00:00.884Z","simulated":false},{"price":8325,"date":"2024-04-22T20:00:00.885Z","simulated":false},{"price":7888,"date":"2024-04-22T21:00:00.886Z","simulated":false}],"devices":[{"id":"generic1","duration":"1","consumptionKWh":"1","isOutOfRange":false,"startTime":"2024-04-22T05:00:00+00:00","endTime":"2024-04-22T06:00:00+00:00","currentCost":"0.053","cheapestCost":"0.053","costSavings":0},{"id":"generic2","duration":"2","consumptionKWh":"1","isOutOfRange":false,"startTime":"2024-04-22T05:00:00+00:00","endTime":"2024-04-22T07:00:00+00:00","currentCost":"0.13","cheapestCost":"0.13","costSavings":0},{"id":"generic3","duration":"3","consumptionKWh":"1","isOutOfRange":false,"startTime":"2024-04-22T05:00:00+00:00","endTime":"2024-04-22T08:00:00+00:00","currentCost":"0.20","cheapestCost":"0.20","costSavings":0},{"id":"generic4","duration":"4","consumptionKWh":"1","isOutOfRange":false,"startTime":"2024-04-22T12:00:00+00:00","endTime":"2024-04-22T16:00:00+00:00","currentCost":"0.33","cheapestCost":"0.30","costSavings":0.030000000000000027},{"id":"generic5","duration":"5","consumptionKWh":"1","isOutOfRange":false,"startTime":"2024-04-22T12:00:00+00:00","endTime":"2024-04-22T17:00:00+00:00","currentCost":"0.45","cheapestCost":"0.42","costSavings":0.030000000000000027},{"id":"generic6","duration":"6","consumptionKWh":"1","isOutOfRange":false,"startTime":"2024-04-22T12:00:00+00:00","endTime":"2024-04-22T18:00:00+00:00","currentCost":"0.57","cheapestCost":"0.54","costSavings":0.029999999999999916},{"id":"generic7","duration":"7","consumptionKWh":"1","isOutOfRange":false,"startTime":"2024-04-22T11:00:00+00:00","endTime":"2024-04-22T18:00:00+00:00","currentCost":"0.70","cheapestCost":"0.67","costSavings":0.029999999999999916},{"id":"generic8","duration":"8","consumptionKWh":"1","isOutOfRange":false,"startTime":"2024-04-22T05:00:00+00:00","endTime":"2024-04-22T13:00:00+00:00","currentCost":"0.77","cheapestCost":"0.77","costSavings":0}],"summary":{"avgPrice":8911,"bestPrice":{"price":5306,"date":"2024-04-22T05:00:00.871Z"},"currentPrice":{"price":5306,"date":"2024-04-22T05:00:00.871Z"},"worstPrice":{"price":13741,"date":"2024-04-22T19:00:00.884Z"}}},"lastUpdated":"2024-04-22 07:10:50"},"pvpcToday":{"avgPrice":8911,"bestPrice":{"date":"2024-04-22T05:00:00.871Z","price":5306,"PMH":368,"TEU":275,"EDCGAS":0,"simulated":false},"currentPrice":{"date":"2024-04-22T05:00:00.871Z","price":5306,"PMH":368,"TEU":275,"EDCGAS":0,"simulated":false},"worstPrice":{"date":"2024-04-22T19:00:00.884Z","price":13741,"PMH":1456,"TEU":7697,"EDCGAS":0,"simulated":false}},"pvpcTomorrow":{}}