{"omie":{"nextPrices":[{"price":8735,"date":"2023-05-31T04:00:00+02:00"},{"price":9567,"date":"2023-05-31T05:00:00+02:00"},{"price":10000,"date":"2023-05-31T06:00:00+02:00"},{"price":10368,"date":"2023-05-31T07:00:00+02:00"},{"price":10023,"date":"2023-05-31T08:00:00+02:00"},{"price":9567,"date":"2023-05-31T09:00:00+02:00"},{"price":7889,"date":"2023-05-31T10:00:00+02:00"},{"price":6850,"date":"2023-05-31T11:00:00+02:00"},{"price":6944,"date":"2023-05-31T12:00:00+02:00"},{"price":6825,"date":"2023-05-31T13:00:00+02:00"},{"price":6723,"date":"2023-05-31T14:00:00+02:00"},{"price":6570,"date":"2023-05-31T15:00:00+02:00"},{"price":6570,"date":"2023-05-31T16:00:00+02:00"},{"price":6884,"date":"2023-05-31T17:00:00+02:00"},{"price":7889,"date":"2023-05-31T18:00:00+02:00"},{"price":8500,"date":"2023-05-31T19:00:00+02:00"},{"price":10500,"date":"2023-05-31T20:00:00+02:00"},{"price":11906,"date":"2023-05-31T21:00:00+02:00"},{"price":11500,"date":"2023-05-31T22:00:00+02:00"},{"price":9661,"date":"2023-05-31T23:00:00+02:00"}],"devices":[{"id":"generic1","duration":"1","consumptionKWh":"1","isOutOfRange":false,"startTime":"2023-05-31T13:00:00+00:00","endTime":"2023-05-31T14:00:00+00:00","currentCost":"0.087","cheapestCost":"0.066","costSavings":0.02099999999999999},{"id":"generic2","duration":"2","consumptionKWh":"1","isOutOfRange":false,"startTime":"2023-05-31T13:00:00+00:00","endTime":"2023-05-31T15:00:00+00:00","currentCost":"0.18","cheapestCost":"0.13","costSavings":0.04999999999999999},{"id":"generic3","duration":"3","consumptionKWh":"1","isOutOfRange":false,"startTime":"2023-05-31T12:00:00+00:00","endTime":"2023-05-31T15:00:00+00:00","currentCost":"0.28","cheapestCost":"0.20","costSavings":0.08000000000000002},{"id":"generic4","duration":"4","consumptionKWh":"1","isOutOfRange":false,"startTime":"2023-05-31T11:00:00+00:00","endTime":"2023-05-31T15:00:00+00:00","currentCost":"0.39","cheapestCost":"0.27","costSavings":0.12},{"id":"generic5","duration":"5","consumptionKWh":"1","isOutOfRange":false,"startTime":"2023-05-31T11:00:00+00:00","endTime":"2023-05-31T16:00:00+00:00","currentCost":"0.49","cheapestCost":"0.34","costSavings":0.14999999999999997},{"id":"generic6","duration":"6","consumptionKWh":"1","isOutOfRange":false,"startTime":"2023-05-31T09:00:00+00:00","endTime":"2023-05-31T15:00:00+00:00","currentCost":"0.58","cheapestCost":"0.40","costSavings":0.17999999999999994},{"id":"generic7","duration":"7","consumptionKWh":"1","isOutOfRange":false,"startTime":"2023-05-31T09:00:00+00:00","endTime":"2023-05-31T16:00:00+00:00","currentCost":"0.66","cheapestCost":"0.47","costSavings":0.19000000000000006},{"id":"generic8","duration":"8","consumptionKWh":"1","isOutOfRange":false,"startTime":"2023-05-31T08:00:00+00:00","endTime":"2023-05-31T16:00:00+00:00","currentCost":"0.73","cheapestCost":"0.55","costSavings":0.17999999999999994}],"summary":{"tendency":"up","avgPrice":8844,"bestPrice":{"price":6570,"date":"2023-05-31T15:00:00+02:00"},"currentPrice":{"price":8735,"date":"2023-05-31T04:00:00+02:00"},"worstPrice":{"price":11906,"date":"2023-05-31T21:00:00+02:00"}}},"pvpc":{"nextPrices":[{"price":12519,"date":"2023-05-31T02:00:00.740Z","simulated":false},{"price":13446,"date":"2023-05-31T03:00:00.741Z","simulated":false},{"price":13621,"date":"2023-05-31T04:00:00.742Z","simulated":false},{"price":13850,"date":"2023-05-31T05:00:00.743Z","simulated":false},{"price":16068,"date":"2023-05-31T06:00:00.744Z","simulated":false},{"price":15206,"date":"2023-05-31T07:00:00.745Z","simulated":false},{"price":18220,"date":"2023-05-31T08:00:00.746Z","simulated":false},{"price":16998,"date":"2023-05-31T09:00:00.747Z","simulated":false},{"price":17128,"date":"2023-05-31T10:00:00.748Z","simulated":false},{"price":16921,"date":"2023-05-31T11:00:00.749Z","simulated":false},{"price":12407,"date":"2023-05-31T12:00:00.750Z","simulated":false},{"price":12281,"date":"2023-05-31T13:00:00.751Z","simulated":false},{"price":12320,"date":"2023-05-31T14:00:00.752Z","simulated":false},{"price":12694,"date":"2023-05-31T15:00:00.753Z","simulated":false},{"price":18572,"date":"2023-05-31T16:00:00.754Z","simulated":false},{"price":19153,"date":"2023-05-31T17:00:00.759Z","simulated":false},{"price":21239,"date":"2023-05-31T18:00:00.760Z","simulated":false},{"price":22809,"date":"2023-05-31T19:00:00.761Z","simulated":false},{"price":18157,"date":"2023-05-31T20:00:00.762Z","simulated":false},{"price":16066,"date":"2023-05-31T21:00:00.763Z","simulated":false}],"devices":[{"id":"generic1","duration":"1","consumptionKWh":"1","isOutOfRange":false,"startTime":"2023-05-31T13:00:00+00:00","endTime":"2023-05-31T14:00:00+00:00","currentCost":"0.13","cheapestCost":"0.12","costSavings":0.010000000000000009},{"id":"generic2","duration":"2","consumptionKWh":"1","isOutOfRange":false,"startTime":"2023-05-31T13:00:00+00:00","endTime":"2023-05-31T15:00:00+00:00","currentCost":"0.26","cheapestCost":"0.25","costSavings":0.010000000000000009},{"id":"generic3","duration":"3","consumptionKWh":"1","isOutOfRange":false,"startTime":"2023-05-31T12:00:00+00:00","endTime":"2023-05-31T15:00:00+00:00","currentCost":"0.40","cheapestCost":"0.37","costSavings":0.030000000000000027},{"id":"generic4","duration":"4","consumptionKWh":"1","isOutOfRange":false,"startTime":"2023-05-31T12:00:00+00:00","endTime":"2023-05-31T16:00:00+00:00","currentCost":"0.53","cheapestCost":"0.50","costSavings":0.030000000000000027},{"id":"generic5","duration":"5","consumptionKWh":"1","isOutOfRange":false,"startTime":"2023-05-31T11:00:00+00:00","endTime":"2023-05-31T16:00:00+00:00","currentCost":"0.70","cheapestCost":"0.67","costSavings":0.029999999999999916},{"id":"generic6","duration":"6","consumptionKWh":"1","isOutOfRange":false,"startTime":"2023-05-31T10:00:00+00:00","endTime":"2023-05-31T16:00:00+00:00","currentCost":"0.85","cheapestCost":"0.84","costSavings":0.010000000000000009},{"id":"generic7","duration":"7","consumptionKWh":"1","isOutOfRange":false,"startTime":"2023-05-31T09:00:00+00:00","endTime":"2023-05-31T16:00:00+00:00","currentCost":"1.0","cheapestCost":"1.0","costSavings":0},{"id":"generic8","duration":"8","consumptionKWh":"1","isOutOfRange":false,"startTime":"2023-05-31T08:00:00+00:00","endTime":"2023-05-31T16:00:00+00:00","currentCost":"1.2","cheapestCost":"1.2","costSavings":0}],"summary":{"tendency":"up","avgPrice":15557,"bestPrice":{"price":12281,"date":"2023-05-31T13:00:00.751Z"},"currentPrice":{"price":12519,"date":"2023-05-31T02:00:00.740Z"},"worstPrice":{"price":22809,"date":"2023-05-31T19:00:00.761Z"}}},"pvpcToday":{"avgPrice":15557,"bestPrice":{"date":"2023-05-31T13:00:00.751Z","TEU":2857,"price":12281,"simulated":false,"EDCGAS":0,"PMH":7720},"currentPrice":{"date":"2023-05-31T02:00:00.740Z","TEU":318,"price":12519,"simulated":false,"EDCGAS":0,"PMH":10271},"tendency":"up","worstPrice":{"date":"2023-05-31T19:00:00.761Z","TEU":7298,"price":22809,"simulated":false,"EDCGAS":0,"PMH":13881}},"pvpcTomorrow":{}}