[{"date":"2026-01-14T00:00:00+01:00","price":14800,"simulated":true},{"date":"2026-01-14T01:00:00+01:00","price":14169,"simulated":true},{"date":"2026-01-14T02:00:00+01:00","price":13938,"simulated":true},{"date":"2026-01-14T03:00:00+01:00","price":13876,"simulated":true},{"date":"2026-01-14T04:00:00+01:00","price":13898,"simulated":true},{"date":"2026-01-14T05:00:00+01:00","price":13831,"simulated":true},{"date":"2026-01-14T06:00:00+01:00","price":13230,"simulated":true},{"date":"2026-01-14T07:00:00+01:00","price":12967,"simulated":true},{"date":"2026-01-14T08:00:00+01:00","price":15516,"simulated":true},{"date":"2026-01-14T09:00:00+01:00","price":15458,"simulated":true},{"date":"2026-01-14T10:00:00+01:00","price":22162,"simulated":true},{"date":"2026-01-14T11:00:00+01:00","price":22049,"simulated":true},{"date":"2026-01-14T12:00:00+01:00","price":22273,"simulated":true},{"date":"2026-01-14T13:00:00+01:00","price":22190,"simulated":true},{"date":"2026-01-14T14:00:00+01:00","price":15362,"simulated":true},{"date":"2026-01-14T15:00:00+01:00","price":15394,"simulated":true},{"date":"2026-01-14T16:00:00+01:00","price":15315,"simulated":true},{"date":"2026-01-14T17:00:00+01:00","price":15365,"simulated":true},{"date":"2026-01-14T18:00:00+01:00","price":22298,"simulated":true},{"date":"2026-01-14T19:00:00+01:00","price":22522,"simulated":true},{"date":"2026-01-14T20:00:00+01:00","price":22443,"simulated":true},{"date":"2026-01-14T21:00:00+01:00","price":22884,"simulated":true},{"date":"2026-01-14T22:00:00+01:00","price":16474,"simulated":true},{"date":"2026-01-14T23:00:00+01:00","price":16429,"simulated":true}]