[{"date":"2025-04-05T00:00:00+02:00","price":7357,"simulated":true},{"date":"2025-04-05T01:00:00+02:00","price":5851,"simulated":true},{"date":"2025-04-05T02:00:00+02:00","price":5764,"simulated":true},{"date":"2025-04-05T03:00:00+02:00","price":5788,"simulated":true},{"date":"2025-04-05T04:00:00+02:00","price":5173,"simulated":true},{"date":"2025-04-05T05:00:00+02:00","price":5492,"simulated":true},{"date":"2025-04-05T06:00:00+02:00","price":5829,"simulated":true},{"date":"2025-04-05T07:00:00+02:00","price":5884,"simulated":true},{"date":"2025-04-05T08:00:00+02:00","price":6000,"simulated":true},{"date":"2025-04-05T09:00:00+02:00","price":4852,"simulated":true},{"date":"2025-04-05T10:00:00+02:00","price":3917,"simulated":true},{"date":"2025-04-05T11:00:00+02:00","price":3837,"simulated":true},{"date":"2025-04-05T12:00:00+02:00","price":3820,"simulated":true},{"date":"2025-04-05T13:00:00+02:00","price":3750,"simulated":true},{"date":"2025-04-05T14:00:00+02:00","price":3749,"simulated":true},{"date":"2025-04-05T15:00:00+02:00","price":3730,"simulated":true},{"date":"2025-04-05T16:00:00+02:00","price":3750,"simulated":true},{"date":"2025-04-05T17:00:00+02:00","price":3860,"simulated":true},{"date":"2025-04-05T18:00:00+02:00","price":4852,"simulated":true},{"date":"2025-04-05T19:00:00+02:00","price":8508,"simulated":true},{"date":"2025-04-05T20:00:00+02:00","price":13429,"simulated":true},{"date":"2025-04-05T21:00:00+02:00","price":13429,"simulated":true},{"date":"2025-04-05T22:00:00+02:00","price":11763,"simulated":true},{"date":"2025-04-05T23:00:00+02:00","price":10738,"simulated":true}]