[{"date":"2025-09-17T00:00:00+02:00","price":14580,"simulated":true},{"date":"2025-09-17T01:00:00+02:00","price":14349,"simulated":true},{"date":"2025-09-17T02:00:00+02:00","price":14159,"simulated":true},{"date":"2025-09-17T03:00:00+02:00","price":13859,"simulated":true},{"date":"2025-09-17T04:00:00+02:00","price":13718,"simulated":true},{"date":"2025-09-17T05:00:00+02:00","price":14069,"simulated":true},{"date":"2025-09-17T06:00:00+02:00","price":14349,"simulated":true},{"date":"2025-09-17T07:00:00+02:00","price":15732,"simulated":true},{"date":"2025-09-17T08:00:00+02:00","price":17602,"simulated":true},{"date":"2025-09-17T09:00:00+02:00","price":15893,"simulated":true},{"date":"2025-09-17T10:00:00+02:00","price":18606,"simulated":true},{"date":"2025-09-17T11:00:00+02:00","price":16572,"simulated":true},{"date":"2025-09-17T12:00:00+02:00","price":14777,"simulated":true},{"date":"2025-09-17T13:00:00+02:00","price":14766,"simulated":true},{"date":"2025-09-17T14:00:00+02:00","price":7884,"simulated":true},{"date":"2025-09-17T15:00:00+02:00","price":8013,"simulated":true},{"date":"2025-09-17T16:00:00+02:00","price":8407,"simulated":true},{"date":"2025-09-17T17:00:00+02:00","price":11380,"simulated":true},{"date":"2025-09-17T18:00:00+02:00","price":21132,"simulated":true},{"date":"2025-09-17T19:00:00+02:00","price":24006,"simulated":true},{"date":"2025-09-17T20:00:00+02:00","price":27832,"simulated":true},{"date":"2025-09-17T21:00:00+02:00","price":34344,"simulated":true},{"date":"2025-09-17T22:00:00+02:00","price":18102,"simulated":true},{"date":"2025-09-17T23:00:00+02:00","price":16890,"simulated":true}]